c8/__init__.py
c8/api.py
c8/apikeys.py
c8/c8ql.py
c8/client.py
c8/collection.py
c8/connection.py
c8/constants.py
c8/cursor.py
c8/exceptions.py
c8/executor.py
c8/fabric.py
c8/graph.py
c8/http.py
c8/job.py
c8/keyvalue.py
c8/request.py
c8/response.py
c8/search.py
c8/stream_apps.py
c8/stream_collection.py
c8/tenant.py
c8/utils.py
c8/version.py
c8/billing/__init__.py
c8/billing/billing_interface.py
c8/billing/core.py
c8/function/__init__.py
c8/function/core.py
c8/function/function_interface.py
c8/redis/__init__.py
c8/redis/core.py
c8/redis/redis_commands.py
c8/redis/redis_interface.py
pyC8-1.1.2.dist-info/LICENSE
pyC8-1.1.2.dist-info/METADATA
pyC8-1.1.2.dist-info/WHEEL
pyC8-1.1.2.dist-info/top_level.txt
pyC8-1.1.2.dist-info/RECORD
