Metadata-Version: 2.1
Name: pyC8
Version: 1.1.2
Summary: Python SDK for Macrometa Global Data Mesh
Home-page: https://www.macrometa.com
Author: Macrometa
Author-email: product@macrometa.com
License: UNKNOWN
Platform: UNKNOWN
Classifier: Intended Audience :: Developers
Classifier: Intended Audience :: End Users/Desktop
Classifier: Intended Audience :: Information Technology
Classifier: Operating System :: MacOS
Classifier: Operating System :: Microsoft :: Windows
Classifier: Operating System :: POSIX
Classifier: Operating System :: Unix
Classifier: Programming Language :: Python
Classifier: Programming Language :: Python :: 3
Classifier: Topic :: Documentation :: Sphinx
License-File: LICENSE
Requires-Dist: requests >=2.31.0
Requires-Dist: six
Requires-Dist: websocket-client ==0.57.0
